[{

        "No":1,
        "question":"ข้อมูลในข้อใด  หมายถึงตัวอักขระ?",
        "answer":"'5'",
        "fake":["(5)","5","\"5\""]
        
    },{
        "No":2,
        "question":"ข้อมูลในข้อใด  หมายถึงข้อความ?",
        "answer":"\"5\"",
        "fake":["(5)","5","'5'"]
        

    },{
        "No":3,
        "question":"จากรูป ส่วนของโปรแกรม ถ้า  n = 6 แล้ว  ค่าผลลัพธ์สุดท้ายของ  f   มีค่าเท่าใด?",
        "answer":"30",
        "fake":["720","120","ไม่มีข้อถูก"],
        "img":"challenge_3.jpg"
    },{
        "No":4,
        "question":"จากรูป หลังจากจบการทำงานแล้ว  ค่าของ  i มีค่าเป็นเท่าใด",
        "answer":"ไม่มีข้อถูก",
        "fake":["7","9","11"],
        "img":"challenge_4.jpg"
    },{
        "No":5,
        "question":"จากรูป ส่วนของโปรแกรมนี้ จะให้ค่าผลลัพธ์เป็นอย่างไร",
        "answer":"5",
        "fake":["5.24","5.2","0"],
        "img":"challenge_5.jpg"
    },{
        "No":6,
        "question":"ข้อใดเป็นผลลัพธ์ที่ได้จากโค้ด printf(“‘I am a programmer.’”);",
        "answer":"‘I am a programmer.’",
        "fake":["\"‘I am a programmer.’\"","I am a programmer","\"I am a programmer.\""]
        
    },{
        "No":7,
        "question":"ผลลัพธ์ของโค้ด printf(\"%d + %d = %d\", 1, 2, 3); คือข้อใด",
        "answer":"1 + 2 = 3",
        "fake":["%d + %d = %d","%d + %d = %d,1,2,3","ไม่มีข้อถูก"]
       
    },{
        "No":8,
        "question":"\"…ไม่ว่าเงื่อนไขจะจริงหรือไม่ คำสั่งทุกคำสั่งจะถูกทำงานไปแล้ว 1 ครั้งเสมอ…\" ข้อความนี้เกี่ยวข้องกับคำสั่งใด",
        "answer":"do-while",
        "fake":["if-else","while","switch case"]
        
    },{
        "No":9,
        "question":"จากรูป ข้อใดไม่ถูกต้อง",
        "answer":"x++ คือเพิ่มค่า x ทีละ 2",
        "fake":["ตัวแปรชื่อ x","ให้พิมพ์ค่า x ซ้ำ ๆ กัน โดยห่างกันเป็นระยะ ๆ ใน 1 บรรทัด","เมื่อ x มีค่ามากกว่า 8 จะทำให้เงื่อนไขเป็นเท็จ"],
        "img":"challenge_9"
    },{
        "No":10,
        "question":"ข้อใดเป็นชื่อตัวแปรไม่ได้",
        "answer":"%boy",
        "fake":["address_2","g5","customerName"]
        
    },{
        "No":11,
        "question":"กำหนดให้ int a=7,b=3,c=2 จงหาผลลัพธ์ของ b/a+c*a",
        "answer":"14",
        "fake":["10","11","12"]
        
    },{
        "No":12,
        "question":"ผลลัพธ์ที่ได้จากการรันโปรแกรมเมื่อกำหนดให้ input = 15",
        "answer":"15 is an odd integer",
        "fake":["15 is an even integer","15 is an odd ","15 is an even"],
        "img":"challenge_12"
    },{
        "No":13,
        "question":"ผลลัพธ์ที่ได้จากการรันโปรแกรมเมื่อกำหนดให้ input คือ 20 50",
        "answer":"70",
        "fake":["50","20","80"],
        "img":"challenge_13"
    },{
        "No":14,
        "question":"ผลลัพธ์ที่ได้จากการรันโปรแกรม",
        "answer":"LMX",
        "fake":["LXM","MXL","XML"],
        "img":"challenge_14"
    },{
        "No":15,
        "question":"ผลลัพธ์ที่ได้จากการรันโปรแกรม",
        "answer":"33",
        "fake":["23","3","13"],
        "img":"challenge_15"
    },{
        "No":16,
        "question":"ผลลัพธ์ที่ได้จากการรันโปรแกรมเมื่อกำหนดให้ input คือ 45",
        "answer":"113.00",
        "fake":["113","113.000000","133.0"],
        "img":"challenge_16"
    },{
        "No":17,
        "question":"ผลลัพธ์ที่ได้จากการรันโปรแกรมเมื่อกำหนดให้ input คือ 15",
        "answer":"9.320568",
        "fake":["9","9.3","10"],
        "img":"challenge_17"
    },{
        "No":18,
        "question":"จากโปรแกรมจงเติมคำตอบที่ถูกต้องใน <...?..>",
        "answer":"%f",
        "fake":["%d","%c","%.2d"],
        "img":"challenge_18"
    },{
        "No":19,
        "question":"ผลลัพธ์ที่ได้จากการรันโปรแกรมเมื่อกำหนดให้ input คือ 50 70",
        "answer":"60",
        "fake":["50","70","55"],
        "img":"challenge_19"
    },{
        "No":20,
        "question":"ผลลัพธ์ที่ได้จากการรันโปรแกรม",
        "answer":"4.00",
        "fake":["4","4.0","4.000"],
        "img":"challenge_20"
    },{
        "No":41,
        "question":"โปรแกรมภาษาซีจะเริ่มทำงานจากฟังก์ชันใด",
        "answer":"main",
        "fake":["include","library","declare"]
        
    },{
        "No":42,
        "question":"คำสั่งใดไม่ใช่คำสั่งควบคุมให้คอมพิวเตอร์ทำงานในลักษณะวนซ้ำเป็นวงจร",
        "answer":"if",
        "fake":["for","while","do-while"]
       
    },{
        "No":43,
        "question":" ข้อใดเรียงล าดับขนาดข้อมูลของตัวแปรจากน้อยไปมากได้ถูกต้อง ",
        "answer":"char, unsigned int, float, double",
        "fake":["double, float, long, unsigned int","long, unsigned long, float, double","unsigned int, char, float, double"],
        
    },{
        "No":44,
        "question":"ค าสั่งใดที่ใช้ในการลบไฟล์",
        "answer":"Delete",
        "fake":["Remove","Open","Rename"]
    },{
        "No":45,
        "question":"ข้อใดคือเลขฐาน 8 ของ AF16",
        "answer":"236",
        "fake":["184","219","257"]
    },{
        "No":46,
        "question":"จากรูป โปรแกรมนี้เป็นโปรแกรมใด",
        "answer":"โปรแกรมหาค่าเฉลี่ย",
        "fake":["โปรแกรมหาค่ามากที่สุด","โปรแกรมหาค่าน้อยที่สุด","โปรแกรมหาค่าผลรวม"],
        "img":"challenge_46_47.jpg"
    },{
        "No":47,
        "question":"จากรูป ถ้า  ค่าของ  a = 5;  b = 10;  c = 15;   ค่า   d  มีค่าเท่าใด",
        "answer":"10",
        "fake":["5","15","15.00"],
        "img":"challenge_46_47.jpg"
    },{
        "No":48,
        "question":"",
        "answer":"",
        "fake":[""],
        "img":""
    },{
        "No":49,
        "question":"",
        "answer":"",
        "fake":[""],
        "img":""
    },{
        "No":50,
        "question":"",
        "answer":"",
        "fake":[""],
        "img":""
    }

]
